sdf/__init__.py
sdf/d2.py
sdf/d3.py
sdf/dn.py
sdf/ease.py
sdf/errors.py
sdf/mesh.py
sdf/progress.py
sdf/stl.py
sdf/text.py
sdf/units.py
sdf/util.py
sdfcad-0.5.2.dist-info/LICENSE.md
sdfcad-0.5.2.dist-info/METADATA
sdfcad-0.5.2.dist-info/WHEEL
sdfcad-0.5.2.dist-info/RECORD
