Metadata-Version: 2.1
Name: sdfcad
Version: 0.5.2
Summary: Simple 3D mesh generation with Python based on signed distance functions
License: MIT
Author: Yann Büchau
Author-email: nobodyinperson@posteo.de
Requires-Python: >=3.10,<4.0
Classifier: License :: OSI Approved :: MIT License
Classifier: Programming Language :: Python :: 3
Classifier: Programming Language :: Python :: 3.10
Classifier: Programming Language :: Python :: 3.11
Classifier: Programming Language :: Python :: 3.12
Provides-Extra: jupyter
Requires-Dist: Pillow (>=10.0.1,<11.0.0)
Requires-Dist: Pint (>=0.22,<0.23)
Requires-Dist: ipython (>=8.15.0,<9.0.0) ; extra == "jupyter"
Requires-Dist: ipywidgets (>=8.1.1,<9.0.0) ; extra == "jupyter"
Requires-Dist: jupyterlab (>=4.0.6,<5.0.0) ; extra == "jupyter"
Requires-Dist: matplotlib (>=3.8.0,<4.0.0)
Requires-Dist: meshio (>=5.3.4,<6.0.0)
Requires-Dist: numpy (>=1,<2)
Requires-Dist: pyvista (>=0.42.2,<0.43.0) ; extra == "jupyter"
Requires-Dist: rich (>=13.5.3,<14.0.0)
Requires-Dist: scikit-image (>=0.17)
Requires-Dist: scipy (>=1,<2)
Requires-Dist: trame (>=3.2.6,<4.0.0) ; extra == "jupyter"
Requires-Dist: trame-vtk (>=2.5.8,<3.0.0) ; extra == "jupyter"
Requires-Dist: trame-vuetify (>=2.3.1,<3.0.0) ; extra == "jupyter"
